ribocutter/__init__.py
ribocutter/__main__.py
ribocutter-0.1.1.dist-info/LICENSE
ribocutter-0.1.1.dist-info/METADATA
ribocutter-0.1.1.dist-info/WHEEL
ribocutter-0.1.1.dist-info/entry_points.txt
ribocutter-0.1.1.dist-info/top_level.txt
ribocutter-0.1.1.dist-info/RECORD
